{
	"mias": [
		{
			"name": "8-Bit Slasher 4-in-1 Horror Demakes (World) (Aftermarket) (Unl).nes",
			"crc": "1e4d95a6"
		},
		{
			"name": "Biocats (World) (Uk) (v1.1) (2025-03-10) (Aftermarket) (Unl).nes",
			"crc": "25abe5b9"
		},
		{
			"name": "Bobby Six Seven - Time-Traveling Detective (USA) (Aftermarket) (Unl).nes",
			"crc": "f6dc9ebd"
		},
		{
			"name": "Candelabra - Estoscerro (World) (Aftermarket) (Unl).nes",
			"crc": "777c773f"
		},
		{
			"name": "Changeable Guardian Estique (USA, Europe) (Aftermarket) (Unl).nes",
			"crc": "a1c3bd5b"
		},
		{
			"name": "Chibi Monster Br4wl (World) (Aftermarket) (Unl).nes",
			"crc": "18054d00"
		},
		{
			"name": "Christmas Crisis 2 (USA) (Aftermarket) (Unl).nes",
			"crc": "947babc3"
		},
		{
			"name": "Data Man (World) (Aftermarket) (Unl).nes",
			"crc": "9b8e3a65"
		},
		{
			"name": "Gemaboy Zero (World) (2025-04-03) (Aftermarket) (Unl).nes",
			"crc": "28e9d1d1"
		},
		{
			"name": "Hazard - Let Us Out! (World) (Aftermarket) (Unl).nes",
			"crc": "d552124f"
		},
		{
			"name": "KUBO 3 (USA) (En,Ja,Fr) (Limited Run Games) (Aftermarket) (Unl).nes",
			"crc": "6d907e9d"
		},
		{
			"name": "Knight on the Moon (World) (Flash saving) (Aftermarket) (Unl).nes",
			"crc": "d19ef7b4"
		},
		{
			"name": "Knight on the Moon (World) (No flash saving) (Aftermarket) (Unl).nes",
			"crc": "d5eff5e2"
		},
		{
			"name": "Knight on the Moon (World) (Rev 3) (Flash saving) (Aftermarket) (Unl).nes",
			"crc": "fb1e4103"
		},
		{
			"name": "Knight on the Moon (World) (Rev 3) (No flash saving) (Aftermarket) (Unl).nes",
			"crc": "2f27564f"
		},
		{
			"name": "Mad Wizard, The - A Candelabra Chronicle (World) (Kickstarter) (Aftermarket) (Unl).nes",
			"crc": "0dd1075a"
		},
		{
			"name": "Orebody - Binder's Tale (World) (Aftermarket) (Unl).nes",
			"crc": "b03f17e1"
		},
		{
			"name": "PLOID (World) (5th Anniversary Edition) (Aftermarket) (Unl).nes",
			"crc": "c3a14eff"
		},
		{
			"name": "Relic Dungeon (World) (Aftermarket) (Unl).nes",
			"crc": "39601904"
		},
		{
			"name": "Relic Dungeon (World) (v1.1) (Aftermarket) (Unl).nes",
			"crc": "e3da8d28"
		},
		{
			"name": "Rise of Amondus, The (World) (Aftermarket) (Unl).nes",
			"crc": "5c2fbd08"
		},
		{
			"name": "Save the Kuin (World) (Aftermarket) (Unl).nes",
			"crc": "832e87a6"
		},
		{
			"name": "Save the Kuin - Grass Mini Game (World) (Aftermarket) (Unl).nes",
			"crc": "eff7c5e7"
		},
		{
			"name": "Super Cambur 2 - Multiverse Chaos (World) (2025-03-14) (Aftermarket) (Unl).nes",
			"crc": "5ed03b28"
		},
		{
			"name": "Super Cambur Origins (World) (2025-03-14) (Aftermarket) (Unl).nes",
			"crc": "27b73ecf"
		},
		{
			"name": "Trial of Kharzoid, The (World) (2025-01-27) (Aftermarket) (Unl).nes",
			"crc": "8af8e1c6"
		},
		{
			"name": "Trial of Kharzoid, The (World) (2025-04-23) (Aftermarket) (Unl).nes",
			"crc": "1dd8a57c"
		}
	]
}