{
	"mias": [
		{
			"name": "Another Century's Episode R - Dai-2-dan Tentou Hansokuyou DVD (Japan) (Promo).iso",
			"crc": "4c985627"
		},
		{
			"name": "Conveni DS, The - Otona no Keieiryoku Training (Japan) (Promo).iso",
			"crc": "77c4e5c1"
		},
		{
			"name": "Iris no Atelier - Eternal Mana (Japan) (Promo).iso",
			"crc": "2713b1d0"
		},
		{
			"name": "Square Enix - Tentou Promotion DVD - Ver. 200706 (Japan) (Promo).iso",
			"crc": "acad1ee1"
		},
		{
			"name": "Square Enix - Tentou Promotion DVD - Ver. 200711 (Japan) (Promo).iso",
			"crc": "2e4ac7b1"
		},
		{
			"name": "Square Enix - Tentou Promotion DVD - Ver. 201308 (Japan) (Promo).iso",
			"crc": "5e440b88"
		},
		{
			"name": "Square Enix - Tentou Promotion DVD - Ver. 201708 (Japan) (Promo).iso",
			"crc": "ab21db8c"
		},
		{
			"name": "Square Enix - Tentou Promotion DVD - Ver. 201809 (Japan) (Promo).iso",
			"crc": "68c1a835"
		},
		{
			"name": "Taiko no Tatsujin - Appare San-dai-me + Taiko no Tatsujin - Wakuwaku Anime Matsuri (Japan) (Promo).iso",
			"crc": "226b599c"
		}
	]
}