{
	"description": {
		"name": "Benesse - Pocket Challenge W (No-Intro)",
		"lastUpdated": "12 August 2025",
		"minimumVersion": "2.00"
	},

	"variants": [
		{
			"group": "Shinkenzemi Chuugaku Kouza - Chuugaku Rika Pack",
			"titles": [
				{"searchTerm": "Shinkenzemi Chuugaku Kouza - Chuugaku Rika Pack (1-bunya - Soft 2-bunya Soft Kanzen Taiou Ban)"},
				{"searchTerm": "Shinkenzemi Chuugaku Kouza - Chuugaku Rika Pack", "priority": 2},
				{"searchTerm": "Shinkenzemi Chuugaku Kouza - Chuugaku Rika (1-bunya)", "priority": 2},
				{"searchTerm": "Shinkenzemi Chuugaku Kouza - Chuugaku Rika (2-bunya)", "priority": 3}
			]
		}
	]
}
