{
	"description": {
		"name": "Nintendo - Game Boy (No-Intro)",
		"lastUpdated": "09 March 2024",
		"minimumVersion": "2.02"
	},

	"variants": [
		{
			"group": "A-mazing Tater",
			"titles": [
				{"searchTerm": "A-mazing Tater"},
				{"searchTerm": "Puzzle Boy II"}
			]
		},
		{
			"group": "Action Replay Pro",
			"categories": ["Applications"],
			"titles": [
				{"searchTerm": "Action Replay Pro"}
			]
		},
		{
			"group": "Adventure Island",
			"titles": [
				{"searchTerm": "Adventure Island"},
				{"searchTerm": "Takahashi Meijin no Bouken-jima II"}
			]
		},
		{
			"group": "Adventure Island II - Aliens in Paradise",
			"titles": [
				{"searchTerm": "Adventure Island II - Aliens in Paradise"},
				{"searchTerm": "Takahashi Meijin no Bouken-jima III"}
			],
			"compilations": [
				{"searchTerm": "Mani 4 in 1 - Takahashi Meijin no Bouken-jima II + GB Genjin + Bomber Boy + Milon no Meikyuu Kumikyoku", "titlePosition": 1}
			]
		},
		{
			"group": "Adventures of Lolo",
			"titles": [
				{"searchTerm": "Adventures of Lolo"},
				{"searchTerm": "Lolo no Daibouken"}
			]
		},
		{
			"group": "Adventures of Star Saver, The",
			"titles": [
				{"searchTerm": "Adventures of Star Saver, The"},
				{"searchTerm": "Rubble Saver"}
			]
		},
		{
			"group": "Alien Olympics",
			"titles": [
				{"searchTerm": "Alien Olympics"},
				{"searchTerm": "Alien Games", "priority": 2}
			]
		},
		{
			"group": "Alien vs Predator - The Last of His Clan",
			"titles": [
				{"searchTerm": "Alien vs Predator - The Last of His Clan"},
				{"searchTerm": "Alien vs Predator"}
			]
		},
		{
			"group": "Alleyway",
			"titles": [
				{"searchTerm": "Alleyway"}
			],
			"compilations": [
				{"searchTerm": "Mani 4 in 1 - Tetris + Alleyway + Yakuman + Tennis", "titlePosition": 2}
			]
		},
		{
			"group": "Amazing Penguin",
			"titles": [
				{"searchTerm": "Amazing Penguin"},
				{"searchTerm": "Osawagase! Penguin Boy"}
			]
		},
		{
			"group": "Arcade Classic No. 2 - Centipede & Millipede",
			"titles": [
				{"searchTerm": "Arcade Classic No. 2 - Centipede & Millipede"},
				{"searchTerm": "Centipede (Accolade)", "priority": 2},
				{"searchTerm": "Centipede (Majesco)", "priority": 3}
			]
		},
		{
			"group": "Arcade Classic No. 3 - Galaga & Galaxian",
			"titles": [
				{"searchTerm": "Arcade Classic No. 3 - Galaga & Galaxian"},
				{"searchTerm": "Galaga & Galaxian"}
			]
		},
		{
			"group": "Atomic Punk",
			"titles": [
				{"searchTerm": "Atomic Punk"},
				{"searchTerm": "Bomber Boy"},
				{"searchTerm": "Dynablaster"}
			],
			"compilations": [
				{"searchTerm": "Bomberman Collection"},
				{"searchTerm": "Mani 4 in 1 - Takahashi Meijin no Bouken-jima II + GB Genjin + Bomber Boy + Milon no Meikyuu Kumikyoku", "titlePosition": 3}
			]
		},
		{
			"group": "Avenging Spirit",
			"titles": [
				{"searchTerm": "Avenging Spirit"},
				{"searchTerm": "Phantasm"}
			]
		},
		{
			"group": "Bonk's Adventure",
			"titles": [
				{"searchTerm": "Bonk's Adventure"},
				{"searchTerm": "B.C. Kid"},
				{"searchTerm": "GB Genjin"}
			],
			"compilations": [
				{"searchTerm": "Genjin Collection"},
				{"searchTerm": "Mani 4 in 1 - Takahashi Meijin no Bouken-jima II + GB Genjin + Bomber Boy + Milon no Meikyuu Kumikyoku", "titlePosition": 2}
			]
		},
		{
			"group": "Bonk's Revenge",
			"titles": [
				{"searchTerm": "Bonk's Revenge"},
				{"searchTerm": "B.C. Kid 2"},
				{"searchTerm": "GB Genjin 2"}
			],
			"compilations": [
				{"searchTerm": "Genjin Collection"}
			]
		},
		{
			"group": "Bart Simpson's Escape from Camp Deadly",
			"titles": [
				{"searchTerm": "Bart Simpson's Escape from Camp Deadly"},
				{"searchTerm": "Bart no Survival Camp"}
			]
		},
		{
			"group": "Bases Loaded",
			"titles": [
				{"searchTerm": "Bases Loaded"},
				{"searchTerm": "Baseball Kids"}
			]
		},
		{
			"group": "Battle Arena Toshinden",
			"titles": [
				{"searchTerm": "Battle Arena Toshinden"},
				{"searchTerm": "Nettou Toushinden"}
			]
		},
		{
			"group": "Battle Unit Zeoth",
			"titles": [
				{"searchTerm": "Battle Unit Zeoth"},
				{"searchTerm": "Jet Pack", "priority": 2}
			]
		},
		{
			"group": "Battleship",
			"titles": [
				{"searchTerm": "Battleship"},
				{"searchTerm": "Kaisen Game - Navyblue"}
			]
		},
		{
			"group": "Best of the Best - Championship Karate",
			"titles": [
				{"searchTerm": "Best of the Best - Championship Karate"},
				{"searchTerm": "Kick Boxing, The"}
			]
		},
		{
			"group": "Bill & Ted's Excellent Game Boy Adventure - A Bogus Journey!",
			"titles": [
				{"searchTerm": "Bill & Ted's Excellent Game Boy Adventure - A Bogus Journey!"},
				{"searchTerm": "Bill & Ted's Excellent Portable Adventure - A Bogus Journey! (Retro Collection)"}
			]
		},
		{
			"group": "Bionic Battler",
			"titles": [
				{"searchTerm": "Bionic Battler"},
				{"searchTerm": "VS Battler"}
			]
		},
		{
			"group": "Black Bass - Lure Fishing",
			"titles": [
				{"searchTerm": "Black Bass - Lure Fishing"},
				{"searchTerm": "Hyper Black Bass"}
			]
		},
		{
			"group": "Blades of Steel",
			"titles": [
				{"searchTerm": "Blades of Steel"},
				{"searchTerm": "Konamic Ice Hockey"}
			]
		},
		{
			"group": "Blaster Master Boy",
			"titles": [
				{"searchTerm": "Blaster Master Boy"},
				{"searchTerm": "Blaster Master Jr."},
				{"searchTerm": "Bomber King - Scenario 2"}
			]
		},
		{
			"group": "Blues Brothers, The",
			"titles": [
				{"searchTerm": "Blues Brothers, The"},
				{"searchTerm": "Blues Brothers"}
			]
		},
		{
			"group": "Bobby's World",
			"titles": [
				{"searchTerm": "Bobby's World"},
				{"searchTerm": "Home Alone 2 - Kevin's Dream", "priority": 2}
			]
		},
		{
			"group": "Bomberman GB",
			"titles": [
				{
					"searchTerm": "Bomberman GB",
					"filters": [
						{
							"conditions": {"matchRegions": ["Japan"]},
							"results": {"group": "Wario Blast Featuring Bomberman!"}
						}
					]
				}
			],
			"compilations": [
				{"searchTerm": "Bomberman Collection"}
			]
		},
		{
			"group": "Bomberman GB 2",
			"titles": [
				{
					"searchTerm": "Bomberman GB 2",
					"filters": [
						{
							"conditions": {"matchRegions": ["Japan"]},
							"results": {"group": "Bomberman GB"}
						}
					]
				}
			]
		},
		{
			"group": "Boomer's Adventure in ASMIK World",
			"titles": [
				{"searchTerm": "Boomer's Adventure in ASMIK World"},
				{"searchTerm": "Teke Teke! Asmik-kun World"}
			]
		},
		{
			"group": "Boxxle",
			"titles": [
				{"searchTerm": "Boxxle"},
				{"searchTerm": "Soukoban"}
			]
		},
		{
			"group": "Boxxle II",
			"titles": [
				{"searchTerm": "Boxxle II"},
				{"searchTerm": "Soukoban 2"}
			]
		},
		{
			"group": "Brain Bender",
			"titles": [
				{"searchTerm": "Brain Bender"},
				{"searchTerm": "Migrain"},
				{"searchTerm": "Mind Bender", "priority": 2}
			]
		},
		{
			"group": "Bubble Bobble",
			"titles": [
				{"searchTerm": "Bubble Bobble"}
			],
			"compilations": [
				{"searchTerm": "Taito Variety Pack"},
				{"searchTerm": "Mani 4 in 1 - Bubble Bobble + Elevator Action + Chase H.Q. + Sagaia"}
			]
		},
		{
			"group": "Bubble Bobble Part 2",
			"titles": [
				{"searchTerm": "Bubble Bobble Part 2"},
				{"searchTerm": "Bubble Bobble Junior"}
			]
		},
		{
			"group": "Bugs Bunny Crazy Castle, The",
			"titles": [
				{"searchTerm": "Bugs Bunny Crazy Castle, The"}
			],
			"compilations": [
				{"searchTerm": "Bugs Bunny Collection"}
			]
		},
		{
			"group": "Bugs Bunny Crazy Castle 2, The",
			"titles": [
				{"searchTerm": "Bugs Bunny Crazy Castle 2, The"},
				{
					"searchTerm": "Hugo",
					"filters": [
						{
							"conditions": {"matchString": "Homebrew"},
							"results": {"group": "Hugo (Homebrew)"}
						}
					]

				},
				{
					"searchTerm": "Mickey Mouse",
					"filters": [
						{
							"conditions" : {"matchRegions": ["Japan"]},
							"results": {"group": "Bugs Bunny Crazy Castle, The"}
						}
					]
				},
				{"searchTerm": "Mickey Mouse II"}
			],
			"compilations": [
				{"searchTerm": "Bugs Bunny Collection"}
			]
		},
		{
			"group": "Burai Fighter Deluxe",
			"titles": [
				{"searchTerm": "Burai Fighter Deluxe"},
				{"searchTerm": "Burai Senshi Deluxe"}
			]
		},
		{
			"group": "Bust-A-Move 2 - Arcade Edition",
			"titles": [
				{"searchTerm": "Bust-A-Move 2 - Arcade Edition"},
				{"searchTerm": "Puzzle Bobble GB"}
			]
		},
		{
			"group": "Buster Bros.",
			"titles": [
				{"searchTerm": "Buster Bros."},
				{"searchTerm": "Pang"}
			]
		},
		{
			"group": "Castelian",
			"titles": [
				{"searchTerm": "Castelian"},
				{"searchTerm": "Kyoro-chan Land"}
			]
		},
		{
			"group": "Castle Quest",
			"titles": [
				{"searchTerm": "Castle Quest"},
				{"searchTerm": "Triumph", "priority": 2}
			]
		},
		{
			"group": "Castlevania - The Adventure",
			"titles": [
				{"searchTerm": "Castlevania - The Adventure"},
				{"searchTerm": "Dracula Densetsu"}
			]
		},
		{
			"group": "Castlevania II - Belmont's Revenge",
			"titles": [
				{"searchTerm": "Castlevania II - Belmont's Revenge"},
				{"searchTerm": "Dracula Densetsu II"}
			]
		},
		{
			"group": "Castlevania Legends",
			"titles": [
				{"searchTerm": "Castlevania Legends"},
				{"searchTerm": "Akumajou Dracula - Shikkoku Taru Zensoukyoku - Dark Night Prelude"}
			]
		},
		{
			"group": "Catrap",
			"titles": [
				{"searchTerm": "Catrap"},
				{"searchTerm": "Pitman"},
				{"searchTerm": "Power Paws", "priority": 2}
			]
		},
		{
			"group": "Chase H.Q.",
			"titles": [
				{"searchTerm": "Chase H.Q."},
				{"searchTerm": "Taito Chase H.Q."}
			],
			"compilations": [
				{"searchTerm": "Taito Variety Pack"},
				{"searchTerm": "Mani 4 in 1 - Bubble Bobble + Elevator Action + Chase H.Q. + Sagaia"}
			]
		},
		{
			"group": "Chikyuu Kaihou Gun ZAS",
			"titles": [
				{"searchTerm": "Chikyuu Kaihou Gun ZAS"},
				{"searchTerm": "ZAS", "priority": 2}
			]
		},
		{
			"group": "Choplifter II - Rescue & Survive",
			"titles": [
				{"searchTerm": "Choplifter II - Rescue & Survive"},
				{"searchTerm": "Choplifter II"}
			]
		},
		{
			"group": "Contra - The Alien Wars",
			"titles": [
				{"searchTerm": "Contra - The Alien Wars"},
				{"searchTerm": "Contra Spirits"},
				{"searchTerm": "Probotector 2"}
			]
		},
		{
			"group": "Cool Ball",
			"titles": [
				{"searchTerm": "Cool Ball"},
				{"searchTerm": "Pop Up"}
			]
		},
		{
			"group": "Cyraid",
			"titles": [
				{"searchTerm": "Cyraid"},
				{"searchTerm": "Bakuretsu Senshi Warrior"}
			]
		},
		{
			"group": "Daedalian Opus",
			"titles": [
				{"searchTerm": "Daedalian Opus"},
				{"searchTerm": "Bouken! Puzzle Road"}
			]
		},
		{
			"group": "Daffy Duck",
			"titles": [
				{"searchTerm": "Daffy Duck"},
				{"searchTerm": "Looney Tunes Series - Daffy Duck"}
			]
		},
		{
			"group": "David Crane's The Rescue of Princess Blobette",
			"titles": [
				{"searchTerm": "David Crane's The Rescue of Princess Blobette"},
				{"searchTerm": "Fushigi na Blobby - Princess Blob o Sukue!"}
			]
		},
		{
			"group": "Dennis the Menace",
			"titles": [
				{"searchTerm": "Dennis the Menace"},
				{"searchTerm": "Dennis"}
			]
		},
		{
			"group": "Dexterity",
			"titles": [
				{"searchTerm": "Dexterity"},
				{"searchTerm": "Funny Field"}
			]
		},
		{
			"group": "Doctor GB",
			"titles": [
				{"searchTerm": "Doctor GB Card 16M Loader"},
				{"searchTerm": "Doctor GB Card 4M", "priority": 2}
			]
		},
		{
			"group": "Donkey Kong Land",
			"titles": [
				{
					"searchTerm": "Donkey Kong Land",
					"filters": [
						{
							"conditions": {"matchRegions": ["Japan"]},
							"results": {"group": "Donkey Kong Land 2"}
						}
					]
				},
				{"searchTerm": "Super Donkey Kong GB"}
			]
		},
		{
			"group": "Double Dragon II",
			"titles": [
				{"searchTerm": "Double Dragon II"},
				{"searchTerm": "Nekketsu Kouha Kunio-kun - Bangai Rantou Hen"}
			]
		},
		{
			"group": "Double Dribble - 5 on 5",
			"titles": [
				{"searchTerm": "Double Dribble - 5 on 5"},
				{"searchTerm": "Hyper Dunk"},
				{"searchTerm": "Konamic Basket"}
			]
		},
		{
			"group": "Dragon's Lair - The Legend",
			"titles": [
				{"searchTerm": "Dragon's Lair - The Legend"},
				{"searchTerm": "Dragon's Lair"}
			]
		},
		{
			"group": "Elevator Action",
			"titles": [
				{"searchTerm": "Elevator Action"}
			],
			"compilations": [
				{"searchTerm": "Taito Variety Pack"},
				{"searchTerm": "Mani 4 in 1 - Bubble Bobble + Elevator Action + Chase H.Q. + Sagaia"}
			]
		},
		{
			"group": "Elite Soccer",
			"titles": [
				{"searchTerm": "Elite Soccer"},
				{
					"searchTerm": "Soccer",
					"filters": [
						{
							"conditions": {"matchRegions": ["Japan"]},
							"results": {"group": "Football International"}
						}
					]
				},
				{"searchTerm": "World Cup Striker"}
			]
		},
		{
			"group": "Escape 2042 - The Truth Defenders",
			"titles": [
				{"searchTerm": "Escape 2042 - The Truth Defenders"},
				{"searchTerm": "Escape 2042 - Les Defenseurs de la Verite"}
			]
		},
		{
			"group": "Extra Bases",
			"titles": [
				{"searchTerm": "Extra Bases"},
				{"searchTerm": "Famista"}
			]
		},
		{
			"group": "F-15 Strike Eagle",
			"titles": [
				{"searchTerm": "F-15 Strike Eagle"},
				{"searchTerm": "F-15 Strike Eagle II", "priority": 2}
			]
		},
		{
			"group": "F1 Pole Position",
			"titles": [
				{"searchTerm": "F1 Pole Position"},
				{"searchTerm": "Nakajima Satoru Kanshuu - F-1 Hero GB '92 - The Graded Driver"}
			]
		},
		{
			"group": "Ferrari Grand Prix Challenge",
			"titles": [
				{"searchTerm": "Ferrari Grand Prix Challenge"},
				{"searchTerm": "Ferrari"}
			]
		},
		{
			"group": "Fighting Simulator 2 in 1 - Flying Warriors",
			"titles": [
				{"searchTerm": "Fighting Simulator 2 in 1 - Flying Warriors"},
				{"searchTerm": "Hiryuu no Ken Gaiden"}
			]
		},
		{
			"group": "Final Fantasy Adventure",
			"titles": [
				{"searchTerm": "Final Fantasy Adventure"},
				{"searchTerm": "Mystic Quest"},
				{"searchTerm": "Seiken Densetsu - Final Fantasy Gaiden"}
			]
		},
		{
			"group": "Final Fantasy Legend II",
			"titles": [
				{"searchTerm": "Final Fantasy Legend II"},
				{"searchTerm": "Sa-Ga 2 - Hihou Densetsu"}
			]
		},
		{
			"group": "Final Fantasy Legend III",
			"titles": [
				{"searchTerm": "Final Fantasy Legend III"},
				{"searchTerm": "Sa-Ga 3 - Jikuu no Hasha"}
			]
		},
		{
			"group": "Final Fantasy Legend, The",
			"titles": [
				{"searchTerm": "Final Fantasy Legend, The"},
				{"searchTerm": "Makai Toushi Sa-Ga"}
			]
		},
		{
			"group": "Fish Dude",
			"titles": [
				{"searchTerm": "Fish Dude"},
				{"searchTerm": "Uoozu"}
			]
		},
		{
			"group": "Fist of the North Star",
			"titles": [
				{"searchTerm": "Fist of the North Star"},
				{"searchTerm": "Hokuto no Ken - Seizetsu Juuban Shoubu"}
			]
		},
		{
			"group": "Flipull",
			"titles": [
				{"searchTerm": "Flipull"},
				{"searchTerm": "Flipull - An Exciting Cube Game"}
			]
		},
		{
			"group": "Fortified Zone",
			"titles": [
				{"searchTerm": "Fortified Zone"},
				{"searchTerm": "Ikari no Yousai"}
			]
		},
		{
			"group": "From TV Animation Slam Dunk - Gakeppuchi no Kesshou League",
			"titles": [
				{"searchTerm": "From TV Animation Slam Dunk - Gakeppuchi no Kesshou League"},
				{"searchTerm": "From TV Animation Slam Dunk Limited Edition", "priority": 2}
			]
		},
		{
			"group": "Game Boy Aging Cartridge",
			"categories": ["Applications"],
			"titles": [
				{"searchTerm": "Game Boy Aging Cartridge"}
			]
		},
		{
			"group": "Game Boy Camera Gold",
			"categories": ["Applications"],
			"titles": [
				{"searchTerm": "Game Boy Camera Gold"},
				{"searchTerm": "Game Boy Camera", "priority": 2},
				{"searchTerm": "Pocket Camera"}
			]
		},
		{
			"group": "Game Boy Controller Kensa Cartridge",
			"categories": ["Applications"],
			"titles": [
				{"searchTerm": "Game Boy Controller Kensa Cartridge"}
			]
		},
		{
			"group": "Game Boy Datenlogger 1",
			"categories": ["Applications"],
			"titles": [
				{"searchTerm": "Game Boy Datenlogger 1"}
			]
		},
		{
			"group": "Game Boy Digital Sampling Oscilloscope",
			"categories": ["Applications"],
			"titles": [
				{"searchTerm": "Game Boy Digital Sampling Oscilloscope"}
			]
		},
		{
			"group": "Game Boy Gallery",
			"titles": [
				{
					"searchTerm": "Game Boy Gallery",
					"filters": [
						{
							"conditions": {"matchRegions": ["Japan"]},
							"results": {"group": "Game & Watch Gallery"}
						}
					]
				}
			]
		},
		{
			"group": "Game Boy Gallery 2",
			"titles": [
				{
					"searchTerm": "Game Boy Gallery 2",
					"filters": [
						{
							"conditions": {"matchRegions": ["Australia"]},
							"results": {"group": "Game & Watch Gallery"}
						}
					]
				}
			]
		},
		{
			"group": "Game Genie",
			"categories": ["Applications"],
			"titles": [
				{"searchTerm": "Game Genie"}
			]
		},
		{
			"group": "GameShark",
			"categories": ["Applications"],
			"titles": [
				{"searchTerm": "GameShark"}
			]
		},
		{
			"group": "Ganso!! Yancha Maru",
			"titles": [
				{"searchTerm": "Ganso!! Yancha Maru"}
			],
			"compilations": [
				{"searchTerm": "Mani 4 in 1 - R-Type II + Saigo no Nindou + Ganso!! Yancha Maru + Shisenshou - Match-Mania", "titlePosition": 3}
			]
		},
		{
			"group": "Gargoyle's Quest",
			"titles": [
				{"searchTerm": "Gargoyle's Quest"},
				{"searchTerm": "Red Arremer - Makaimura Gaiden"}
			]
		},
		{
			"group": "GB Genjin Land - Viva! Chikkun Oukoku",
			"titles": [
				{"searchTerm": "GB Genjin Land - Viva! Chikkun Oukoku"}
			],
			"compilations": [
				{"searchTerm": "Genjin Collection"}
			]
		},
		{
			"group": "Genki Bakuhatsu Gambaruger",
			"titles": [
				{"searchTerm": "Genki Bakuhatsu Gambaruger"}
			],
			"compilations": [
				{"searchTerm": "Mani 4 in 1 - Genki Bakuhatsu Gambaruger + Zettai Muteki Raijin-Oh + Zoids Densetsu + Miracle Adventure of Esparks - Ushinawareta Seiseki Perivron", "titlePosition": 1}
			]
		},
		{
			"group": "Goal!",
			"titles": [
				{"searchTerm": "Goal!"},
				{"searchTerm": "Jaleco J.Cup Soccer"},
				{"searchTerm": "Takeda Nobuhiro no Ace Striker", "priority": 2}
			]
		},
		{
			"group": "Godzilla",
			"titles": [
				{"searchTerm": "Godzilla"},
				{"searchTerm": "Gojira-kun - Kaijuu Daikoushin"}
			]
		},
		{
			"group": "Gradius - The Interstellar Assault",
			"titles": [
				{"searchTerm": "Gradius - The Interstellar Assault"},
				{"searchTerm": "Nemesis II"},
				{"searchTerm": "Nemesis II - The Return of the Hero"}
			]
		},
		{
			"group": "Great Greed",
			"titles": [
				{"searchTerm": "Great Greed"},
				{"searchTerm": "Vitamina Oukoku Monogatari"}
			]
		},
		{
			"group": "HAL Wrestling",
			"titles": [
				{"searchTerm": "HAL Wrestling"},
				{"searchTerm": "Pro Wrestling"}
			]
		},
		{
			"group": "Hammerin' Harry",
			"titles": [
				{"searchTerm": "Hammerin' Harry"},
				{"searchTerm": "Daiku no Gen-san - Ghost Building Company", "localNames": {"japanese": "大工の源さん ゴーストビルディングカンパニー"}}
			]
		},
		{
			"group": "Harvest Moon GB",
			"titles": [
				{"searchTerm": "Harvest Moon GB"},
				{"searchTerm": "Bokujou Monogatari GB"}
			]
		},
		{
			"group": "Heiankyo Alien",
			"titles": [
				{"searchTerm": "Heiankyo Alien"},
				{"searchTerm": "Heiankyou Alien"}
			]
		},
		{
			"group": "Heavyweight Championship Boxing",
			"titles": [
				{"searchTerm": "Heavyweight Championship Boxing"},
				{"searchTerm": "Boxing"}
			]
		},
		{
			"group": "Hunt for Red October, The",
			"titles": [
				{"searchTerm": "Hunt for Red October, The"},
				{"searchTerm": "Red October o Oe!"}
			]
		},
		{
			"group": "Indiana Jones and the Last Crusade",
			"titles": [
				{"searchTerm": "Indiana Jones and the Last Crusade"},
				{"searchTerm": "Indiana Jones - Saigo no Seisen"}
			]
		},
		{
			"group": "InfoGenius Productivity Pak - Personal Organizer and Phone Book",
			"categories": ["Applications", "Educational"],
			"titles": [
				{"searchTerm": "InfoGenius Productivity Pak - Personal Organizer and Phone Book"},
				{"searchTerm": "InfoGenius Systems - Personal Organizer with Phone Book"}
			]
		},
		{
			"group": "InfoGenius Productivity Pak - Berlitz French Translator",
			"categories": ["Applications", "Educational"],
			"titles": [
				{"searchTerm": "InfoGenius Productivity Pak - Berlitz French Translator"}
			]
		},
		{
			"group": "InfoGenius Productivity Pak - Berlitz German Translator",
			"categories": ["Applications", "Educational"],
			"titles": [
				{"searchTerm": "InfoGenius Productivity Pak - Berlitz German Translator"}
			]
		},
		{
			"group": "InfoGenius Productivity Pak - Berlitz Japanese Translator",
			"categories": ["Applications", "Educational"],
			"titles": [
				{"searchTerm": "InfoGenius Productivity Pak - Berlitz Japanese Translator"}
			]
		},
		{
			"group": "InfoGenius Productivity Pak - Berlitz Spanish Translator",
			"categories": ["Applications", "Educational"],
			"titles": [
				{"searchTerm": "InfoGenius Productivity Pak - Berlitz Spanish Translator"}
			]
		},
		{
			"group": "InfoGenius Productivity Pak - Frommer's Travel Guide",
			"categories": ["Applications", "Educational"],
			"titles": [
				{"searchTerm": "InfoGenius Productivity Pak - Frommer's Travel Guide"}
			]
		},
		{
			"group": "InfoGenius Productivity Pak - Spell Checker and Calculator",
			"categories": ["Applications", "Educational"],
			"titles": [
				{"searchTerm": "InfoGenius Productivity Pak - Spell Checker and Calculator"}
			]
		},
		{
			"group": "International Superstar Soccer",
			"titles": [
				{"searchTerm": "International Superstar Soccer"},
				{"searchTerm": "World Soccer GB"}
			]
		},
		{
			"group": "J.League Big Wave Soccer",
			"titles": [
				{"searchTerm": "J.League Big Wave Soccer"},
				{"searchTerm": "Matthias Sammer Soccer"}
			]
		},
		{
			"group": "Jet Pak Jak",
			"titles": [
				{"searchTerm": "Jet Pak Jak"},
				{"searchTerm": "Jet Pak Man", "priority": 2}
			]
		},
		{
			"group": "Jimmy Connors Tennis",
			"titles": [
				{"searchTerm": "Jimmy Connors Tennis"},
				{"searchTerm": "Jimmy Connors no Pro Tennis Tour"},
				{"searchTerm": "Yannick Noah Tennis"}
			]
		},
		{
			"group": "Joe & Mac",
			"titles": [
				{"searchTerm": "Joe & Mac"},
				{"searchTerm": "Joe & Mac - Caveman Ninja"}
			]
		},
		{
			"group": "Kid Dracula",
			"titles": [
				{"searchTerm": "Kid Dracula"},
				{"searchTerm": "Akumajou Special - Boku Dracula-kun"}
			]
		},
		{
			"group": "King of Fighters '95, The",
			"titles": [
				{"searchTerm": "King of Fighters '95, The"},
				{"searchTerm": "Nettou The King of Fighters '95"}
			]
		},
		{
			"group": "King of Fighters, The - Heat of Battle",
			"titles": [
				{"searchTerm": "King of Fighters, The - Heat of Battle"},
				{"searchTerm": "Nettou The King of Fighters '96"}
			]
		},
		{
			"group": "Kingdom Crusade",
			"titles": [
				{"searchTerm": "Kingdom Crusade"},
				{"searchTerm": "Legend of Prince Valiant, The"}
			]
		},
		{
			"group": "Kirby's Block Ball",
			"titles": [
				{"searchTerm": "Kirby's Block Ball"},
				{"searchTerm": "Kirby no Block Ball"}
			]
		},
		{
			"group": "Kirby's Dream Land",
			"titles": [
				{"searchTerm": "Kirby's Dream Land"},
				{"searchTerm": "Hoshi no Kirby"}
			]
		},
		{
			"group": "Kirby's Dream Land 2",
			"titles": [
				{"searchTerm": "Kirby's Dream Land 2"},
				{"searchTerm": "Hoshi no Kirby 2"}
			]
		},
		{
			"group": "Kirby's Pinball Land",
			"titles": [
				{"searchTerm": "Kirby's Pinball Land"},
				{"searchTerm": "Kirby no Pinball"}
			]
		},
		{
			"group": "Kirby's Star Stacker",
			"titles": [
				{"searchTerm": "Kirby's Star Stacker"},
				{"searchTerm": "Kirby no Kirakira Kids"}
			]
		},
		{
			"group": "Krusty's Fun House",
			"titles": [
				{"searchTerm": "Krusty's Fun House"},
				{"searchTerm": "Krusty World"}
			]
		},
		{
			"group": "Kung-Fu Master",
			"titles": [
				{"searchTerm": "Kung-Fu Master"},
				{"searchTerm": "Spartan X"}
			]
		},
		{
			"group": "Kwirk - He's A-maze-ing!",
			"titles": [
				{"searchTerm": "Kwirk - He's A-maze-ing!"},
				{"searchTerm": "Puzzle Boy"}
			]
		},
		{
			"group": "Lawnmower Man, The",
			"titles": [
				{"searchTerm": "Lawnmower Man, The"},
				{"searchTerm": "Virtual Wars"}
			]
		},
		{
			"group": "Lazlos' Leap",
			"titles": [
				{"searchTerm": "Lazlos' Leap"},
				{"searchTerm": "Solitaire"}
			]
		},
		{
			"group": "Legend of Zelda, The - Link's Awakening",
			"titles": [
				{"searchTerm": "Legend of Zelda, The - Link's Awakening"},
				{"searchTerm": "Zelda no Densetsu - Yume o Miru Shima"},
				{"searchTerm": "Legend of Zelda, The - Link's Awakening DX", "priority": 2}
			]
		},
		{
			"group": "Legend of the River King GB",
			"titles": [
				{"searchTerm": "Legend of the River King GB"},
				{"searchTerm": "Kawa no Nushi Tsuri 3"}
			]
		},
		{
			"group": "Looney Tunes",
			"titles": [
				{"searchTerm": "Looney Tunes"},
				{"searchTerm": "Looney Tunes - Bugs Bunny to Yukai na Nakama-tachi"}
			]
		},
		{
			"group": "Lost World, The - Jurassic Park",
			"titles": [
				{"searchTerm": "Lost World, The - Jurassic Park"},
				{"searchTerm": "Monde Perdu, Le - Jurassic Park"}
			]
		},
		{
			"group": "Magnetic Soccer",
			"titles": [
				{"searchTerm": "Magnetic Soccer"},
				{"searchTerm": "Kick Attack", "priority": 2}
			]
		},
		{
			"group": "Malibu Beach Volleyball",
			"titles": [
				{"searchTerm": "Malibu Beach Volleyball"},
				{"searchTerm": "Seaside Volley"}
			]
		},
		{
			"group": "Mario's Picross",
			"titles": [
				{"searchTerm": "Mario's Picross"},
				{"searchTerm": "Mario no Picross"}
			]
		},
		{
			"group": "Maru's Mission",
			"titles": [
				{"searchTerm": "Maru's Mission"},
				{"searchTerm": "Oira Jajamaru! Sekai Daibouken"}
			]
		},
		{
			"group": "Max",
			"titles": [
				{"searchTerm": "Max"},
				{"searchTerm": "Rubble Saver II"}
			]
		},
		{
			"group": "Mega Man - Dr. Wily's Revenge",
			"titles": [
				{"searchTerm": "Mega Man - Dr. Wily's Revenge"},
				{"searchTerm": "Rockman World"}
			]
		},
		{
			"group": "Mega Man II",
			"titles": [
				{"searchTerm": "Mega Man II"},
				{"searchTerm": "Rockman World 2"}
			]
		},
		{
			"group": "Mega Man III",
			"titles": [
				{"searchTerm": "Mega Man III"},
				{"searchTerm": "Rockman World 3"}
			]
		},
		{
			"group": "Mega Man IV",
			"titles": [
				{"searchTerm": "Mega Man IV"},
				{"searchTerm": "Rockman World 4"}
			]
		},
		{
			"group": "Mega Man V",
			"titles": [
				{"searchTerm": "Mega Man V"},
				{"searchTerm": "Rockman World 5"}
			]
		},
		{
			"group": "Megami Tensei Gaiden - Last Bible",
			"titles": [
				{"searchTerm": "Megami Tensei Gaiden - Last Bible"},
				{"searchTerm": "Xin Nushen Zhuansheng Waizhuan - Zuihou de Shengjing", "priority": 2}
			]
		},
		{
			"group": "Mercenary Force",
			"titles": [
				{"searchTerm": "Mercenary Force"},
				{"searchTerm": "Tenjin Kaisen"}
			]
		},
		{
			"group": "Mickey Mouse - Magic Wands!",
			"titles": [
				{"searchTerm": "Mickey Mouse - Magic Wands!"},
				{"searchTerm": "Mickey Mouse V"}
			]
		},
		{
			"group": "Mickey's Dangerous Chase",
			"titles": [
				{"searchTerm": "Mickey's Dangerous Chase"},
				{"searchTerm": "Mickey's Chase"}
			]
		},
		{
			"group": "Milon's Secret Castle",
			"titles": [
				{"searchTerm": "Milon's Secret Castle"},
				{"searchTerm": "Milon no Meikyuu Kumikyoku"}
			],
			"compilations": [
				{"searchTerm": "Mani 4 in 1 - Takahashi Meijin no Bouken-jima II + GB Genjin + Bomber Boy + Milon no Meikyuu Kumikyoku", "titlePosition": 4}
			]
		},
		{
			"group": "Miracle Adventure of Esparks - Ushinawareta Seiseki Perivron",
			"titles": [
				{"searchTerm": "Miracle Adventure of Esparks - Ushinawareta Seiseki Perivron"}
			],
			"compilations": [
				{"searchTerm": "Mani 4 in 1 - Genki Bakuhatsu Gambaruger + Zettai Muteki Raijin-Oh + Zoids Densetsu + Miracle Adventure of Esparks - Ushinawareta Seiseki Perivron", "titlePosition": 4}
			]
		},
		{
			"group": "Mofa Qiu - Magic Ball",
			"titles": [
				{"searchTerm": "Mofa Qiu - Magic Ball", "localNames": {"chinese (traditional)": "魔法球"}},
				{"searchTerm": "Mofa Qiu - Magic Ball (Multicart Rip)", "priority": 2, "localNames": {"chinese (traditional)": "魔法球"}}
			]
		},
		{
			"group": "Mole Mania",
			"titles": [
				{"searchTerm": "Mole Mania"},
				{"searchTerm": "Moguranya"}
			]
		},
		{
			"group": "Mortal Kombat",
			"titles": [
				{"searchTerm": "Mortal Kombat"},
				{"searchTerm": "Mortal Kombat - Shinken Kourin Densetsu"}
			],
			"compilations": [
				{"searchTerm": "Mortal Kombat & Mortal Kombat II"}
			]
		},
		{
			"group": "Mortal Kombat II",
			"titles": [
				{"searchTerm": "Mortal Kombat II"},
				{"searchTerm": "Mortal Kombat II - Kyuukyoku Shinken"}
			],
			"compilations": [
				{"searchTerm": "Mortal Kombat & Mortal Kombat II"}
			]
		},
		{
			"group": "Mystical Ninja Starring Goemon",
			"titles": [
				{"searchTerm": "Mystical Ninja Starring Goemon"},
				{"searchTerm": "Ganbare Goemon - Kurofunetou no Nazo"}
			]
		},
		{
			"group": "Nail 'n Scale",
			"titles": [
				{"searchTerm": "Nail 'n Scale"},
				{"searchTerm": "Dragon Tail"}
			]
		},
		{
			"group": "NFL Quarterback Club II",
			"titles": [
				{"searchTerm": "NFL Quarterback Club II"},
				{"searchTerm": "NFL Quarterback Club '95"}
			]
		},
		{
			"group": "Nigel Mansell's World Championship",
			"titles": [
				{"searchTerm": "Nigel Mansell's World Championship"},
				{"searchTerm": "Nigel Mansell's World Championship Racing", "priority": 2}
			]
		},
		{
			"group": "Nyghtmare - Betrayed",
			"titles": [
				{"searchTerm": "Nyghtmare - Betrayed"},
				{"searchTerm": "Nyghtmare - Betrayed (Alpha A)", "priority": 2}
			]
		},
		{
			"group": "Ninja Boy",
			"titles": [
				{"searchTerm": "Ninja Boy"},
				{"searchTerm": "Super Chinese Land"}
			]
		},
		{
			"group": "Ninja Boy 2",
			"titles": [
				{"searchTerm": "Ninja Boy 2"},
				{"searchTerm": "Super Chinese Land 2"}
			]
		},
		{
			"group": "Ninja Gaiden Shadow",
			"titles": [
				{"searchTerm": "Ninja Gaiden Shadow"},
				{"searchTerm": "Ninja Ryuuken Den - Matenrou Kessen"},
				{"searchTerm": "Shadow Warriors"}
			]
		},
		{
			"group": "Ninja Taro",
			"titles": [
				{"searchTerm": "Ninja Taro"},
				{"searchTerm": "Sengoku Ninja-kun"}
			]
		},
		{
			"group": "Nintendo World Cup",
			"titles": [
				{"searchTerm": "Nintendo World Cup"},
				{"searchTerm": "Nekketsu Koukou Soccer-bu - World Cup Hen"}
			]
		},
		{
			"group": "Nobunaga's Ambition",
			"titles": [
				{"searchTerm": "Nobunaga's Ambition"},
				{"searchTerm": "Nobunaga no Yabou - Game Boy Ban"}
			]
		},
		{
			"group": "Operation C",
			"titles": [
				{"searchTerm": "Operation C"},
				{"searchTerm": "Contra"},
				{"searchTerm": "Probotector"}
			]
		},
		{
			"group": "Otto's Ottifanten - Baby Bruno's Alptraum",
			"titles": [
				{"searchTerm": "Otto's Ottifanten - Baby Bruno's Alptraum"},
				{"searchTerm": "Adventures of Pinocchio, The", "priority": 2}
			]
		},
		{
			"group": "Pac-Attack",
			"titles": [
				{"searchTerm": "Pac-Attack"},
				{"searchTerm": "Pac-Panic"}
			]
		},
		{
			"group": "Parodius",
			"titles": [
				{"searchTerm": "Parodius"},
				{"searchTerm": "Parodius Da!"}
			]
		},
		{
			"group": "Penguin Wars",
			"titles": [
				{"searchTerm": "Penguin Wars"},
				{"searchTerm": "King of the Zoo"},
				{"searchTerm": "Penguin-kun Wars VS."}
			]
		},
		{
			"group": "Perfect Blend",
			"titles": [
				{"searchTerm": "Perfect Blend (Bugfix)"},
				{"searchTerm": "Perfect Blend", "priority": 2}
			]
		},
		{
			"group": "Pinball - Revenge of the 'Gator",
			"titles": [
				{"searchTerm": "Pinball - Revenge of the 'Gator"},
				{"searchTerm": "Pinball - 66hiki no Wani Daikoushin!"}
			]
		},
		{
			"group": "Pocket Monsters - Midori",
			"titles": [
				{"searchTerm": "Pocket Monsters - Midori"},
				{"searchTerm": "Pocket Monsters - Green Version - English Edition", "priority": 2}
			]
		},
		{
			"group": "Pocket Camera",
			"categories": ["Applications"],
			"titles": [
				{"searchTerm": "Pocket Camera"}
			]
		},
		{
			"group": "Pocket Sonar",
			"categories": ["Applications"],
			"titles": [
				{"searchTerm": "Pocket Sonar"}
			]
		},
		{
			"group": "Pokemon - Blue Version",
			"titles": [
				{"searchTerm": "Pokemon - Blue Version"},
				{"searchTerm": "Pocket Monsters - Ao"},
				{"searchTerm": "Pokemon - Blaue Edition"},
				{"searchTerm": "Pokemon - Edicion Azul"},
				{"searchTerm": "Pokemon - Version Bleue"},
				{"searchTerm": "Pokemon - Versione Blu"}
			]
		},
		{
			"group": "Pokemon - Red Version",
			"titles": [
				{"searchTerm": "Pokemon - Red Version"},
				{"searchTerm": "Pocket Monsters - Aka"},
				{"searchTerm": "Pokemon - Edicion Roja"},
				{"searchTerm": "Pokemon - Rote Edition"},
				{"searchTerm": "Pokemon - Version Rouge"},
				{"searchTerm": "Pokemon - Versione Rossa"}
			]
		},
		{
			"group": "Pokemon - Yellow Version - Special Pikachu Edition",
			"titles": [
				{"searchTerm": "Pokemon - Yellow Version - Special Pikachu Edition"},
				{"searchTerm": "Pocket Monsters - Pikachu"},
				{"searchTerm": "Pokemon - Edicion Amarilla - Edicion Especial Pikachu"},
				{"searchTerm": "Pokemon - Gelbe Edition - Special Pikachu Edition"},
				{"searchTerm": "Pokemon - Version Jaune - Edition Speciale Pikachu"},
				{"searchTerm": "Pokemon - Versione Gialla - Speciale Edizione Pikachu"}
			]
		},
		{
			"group": "Pop'n TwinBee",
			"titles": [
				{"searchTerm": "Pop'n TwinBee"},
				{"searchTerm": "TwinBee da!!"}
			]
		},
		{
			"group": "Populous",
			"titles": [
				{"searchTerm": "Populous"},
				{"searchTerm": "Populous Gaiden"}
			]
		},
		{
			"group": "Power Racer",
			"titles": [
				{"searchTerm": "Power Racer"},
				{"searchTerm": "Head On"}
			]
		},
		{
			"group": "Prehistorik Man",
			"titles": [
				{"searchTerm": "Prehistorik Man"},
				{"searchTerm": "P-Man GB"}
			]
		},
		{
			"group": "Pro Action Replay",
			"categories": ["Applications"],
			"titles": [
				{"searchTerm": "Pro Action Replay"}
			]
		},
		{
			"group": "R-Type II",
			"titles": [
				{"searchTerm": "R-Type II"}
			],
			"compilations": [
				{"searchTerm": "Mani 4 in 1 - R-Type II + Saigo no Nindou + Ganso!! Yancha Maru + Shisenshou - Match-Mania", "titlePosition": 1}
			]
		},
		{
			"group": "Radar Mission",
			"titles": [
				{"searchTerm": "Radar Mission"},
				{"searchTerm": "Kaisen Game - Radarmission"}
			]
		},
		{
			"group": "Raging Fighter",
			"titles": [
				{"searchTerm": "Raging Fighter"},
				{"searchTerm": "Outburst"}
			]
		},
		{
			"group": "Real Ghostbusters, The",
			"titles": [
				{"searchTerm": "Real Ghostbusters, The"},
				{"searchTerm": "Garfield Labyrinth"},
				{"searchTerm": "Mickey Mouse IV - Mahou no Labyrinth"}
			]
		},
		{
			"group": "Rodland",
			"titles": [
				{"searchTerm": "Rodland"},
				{"searchTerm": "Yousei Monogatari - Rod Land"}
			]
		},
		{
			"group": "Roger Clemens' MVP Baseball",
			"titles": [
				{"searchTerm": "Roger Clemens' MVP Baseball"},
				{"searchTerm": "MVP Baseball"}
			]
		},
		{
			"group": "Rolan's Curse",
			"titles": [
				{"searchTerm": "Rolan's Curse"},
				{"searchTerm": "Velious - Roland no Majuu"}
			]
		},
		{
			"group": "Rolan's Curse II",
			"titles": [
				{"searchTerm": "Rolan's Curse II"},
				{"searchTerm": "Velious II - Fukushuu no Jashin"}
			]
		},
		{
			"group": "Sagaia",
			"titles": [
				{"searchTerm": "Sagaia"}
			],
			"compilations": [
				{"searchTerm": "Taito Variety Pack"},
				{"searchTerm": "Mani 4 in 1 - Bubble Bobble + Elevator Action + Chase H.Q. + Sagaia"}
			]
		},
		{
			"group": "Saigo no Nindou",
			"titles": [
				{"searchTerm": "Saigo no Nindou"}
			],
			"compilations": [
				{"searchTerm": "Mani 4 in 1 - R-Type II + Saigo no Nindou + Ganso!! Yancha Maru + Shisenshou - Match-Mania", "titlePosition": 2}
			]
		},
		{
			"group": "Samurai Shodown",
			"titles": [
				{"searchTerm": "Samurai Shodown"},
				{"searchTerm": "Nettou Samurai Spirits"}
			]
		},
		{
			"group": "Shisenshou - Match-Mania",
			"titles": [
				{"searchTerm": "Shisenshou - Match-Mania"}
			],
			"compilations": [
				{"searchTerm": "Mani 4 in 1 - R-Type II + Saigo no Nindou + Ganso!! Yancha Maru + Shisenshou - Match-Mania", "titlePosition": 4}
			]
		},
		{
			"group": "Sports Illustrated - Golf Classic",
			"titles": [
				{"searchTerm": "Sports Illustrated - Golf Classic"},
				{"searchTerm": "Golf Classic"}
			]
		},
		{
			"group": "Sea Battle",
			"titles": [
				{"searchTerm": "Sea Battle"},
				{"searchTerm": "Bataille Navale"},
				{"searchTerm": "Schiffe Versenken"},
				{"searchTerm": "Battle Ships", "priority": 2}
			]
		},
		{
			"group": "Serpent",
			"titles": [
				{"searchTerm": "Serpent"},
				{"searchTerm": "Kakomunja"}
			]
		},
		{
			"group": "Shanghai",
			"titles": [
				{"searchTerm": "Shanghai"},
				{"searchTerm": "Shanghai (Activision)"},
				{"searchTerm": "Shanghai (HAL Laboratory)", "priority": 2}
			]
		},
		{
			"group": "Sheep It Up",
			"titles": [
				{"searchTerm": "Sheep It Up"},
				{"searchTerm": "Sheep It Up (CatSkull)", "priority": 2},
				{"searchTerm": "Sheep It Up (Yastuna)", "priority": 3}
			]
		},
		{
			"group": "Simpsons, The - Bart & the Beanstalk",
			"titles": [
				{"searchTerm": "Simpsons, The - Bart & the Beanstalk"},
				{"searchTerm": "Simpsons, The - Bart no Jack to Mame no Ki"}
			]
		},
		{
			"group": "SMARTCOM",
			"categories": ["Applications"],
			"titles": [
				{"searchTerm": "SMARTCOM"}
			]
		},
		{
			"group": "Snoopy's Magic Show",
			"titles": [
				{"searchTerm": "Snoopy's Magic Show"},
				{"searchTerm": "Snoopy - Magic Show"}
			]
		},
		{
			"group": "Snow Brothers",
			"titles": [
				{"searchTerm": "Snow Brothers"},
				{"searchTerm": "Snow Bros. Jr."}
			]
		},
		{
			"group": "Soccer Mania",
			"titles": [
				{"searchTerm": "Soccer Mania"},
				{"searchTerm": "Soccer Boy"}
			]
		},
		{
			"group": "Space Invaders",
			"titles": [
				{
					"searchTerm": "Space Invaders",
					"filters": [
						{
							"conditions": {"matchRegions": ["Japan"]},
							"results": {"group": "Space Invaders (Japan)"}
						}
					]
				}
			]
		},
		{
			"group": "Spanky's Quest",
			"titles": [
				{"searchTerm": "Spanky's Quest"},
				{"searchTerm": "Lucky Monkey"}
			]
		},
		{
			"group": "Speedy Gonzales",
			"titles": [
				{"searchTerm": "Speedy Gonzales"},
				{"searchTerm": "Soreyuke! Speedy Gonzales"}
			]
		},
		{
			"group": "Splitz",
			"titles": [
				{"searchTerm": "Splitz"},
				{"searchTerm": "Splitz - Nigaoe 15 Game"},
				{"searchTerm": "Uchiiwai - Kyoudaijingi no Puzzle Game", "priority": 2}
			]
		},
		{
			"group": "Spot - The Cool Adventure",
			"titles": [
				{"searchTerm": "Spot - The Cool Adventure"},
				{"searchTerm": "McDonaldland"},
				{"searchTerm": "Spot - Cool Adventure"}
			]
		},
		{
			"group": "Spot - The Video Game",
			"titles": [
				{"searchTerm": "Spot - The Video Game"},
				{"searchTerm": "Spot"}
			]
		},
		{
			"group": "Spud's Adventure",
			"titles": [
				{"searchTerm": "Spud's Adventure"},
				{"searchTerm": "Totsugeki Valations"}
			]
		},
		{
			"group": "Spy vs Spy - Operation Boobytrap",
			"titles": [
				{"searchTerm": "Spy vs Spy - Operation Boobytrap"},
				{"searchTerm": "Trappers Tengoku - Spy vs Spy"}
			]
		},
		{
			"group": "Square Deal - The Game of Two-Dimensional Poker",
			"titles": [
				{"searchTerm": "Square Deal - The Game of Two-Dimensional Poker"},
				{"searchTerm": "Cadillac II"}
			]
		},
		{
			"group": "Stop That Roach!",
			"titles": [
				{"searchTerm": "Stop That Roach!"},
				{"searchTerm": "Hoi Hoi - Game Boy Ban"}
			]
		},
		{
			"group": "Sumo Fighter",
			"titles": [
				{"searchTerm": "Sumo Fighter"},
				{"searchTerm": "Sumou Fighter - Toukaidou Basho"}
			]
		},
		{
			"group": "Sunsoft Grand Prix",
			"titles": [
				{"searchTerm": "Sunsoft Grand Prix"},
				{"searchTerm": "F1 Boy"}
			]
		},
		{
			"group": "Super Black Bass",
			"titles": [
				{"searchTerm": "Super Black Bass"},
				{"searchTerm": "Super Black Bass Pocket"}
			]
		},
		{
			"group": "Super Kick Off",
			"titles": [
				{"searchTerm": "Super Kick Off"},
				{"searchTerm": "Pro Soccer"}
			]
		},
		{
			"group": "Super Mario Land 2 - 6 Golden Coins",
			"titles": [
				{"searchTerm": "Super Mario Land 2 - 6 Golden Coins"},
				{"searchTerm": "Super Mario Land 2 - 6-tsu no Kinka"}
			]
		},
		{
			"group": "Sword of Hope II, The",
			"titles": [
				{"searchTerm": "Sword of Hope II, The"},
				{"searchTerm": "Selection II - Ankoku no Fuuin"}
			]
		},
		{
			"group": "Sword of Hope, The",
			"titles": [
				{"searchTerm": "Sword of Hope, The"},
				{"searchTerm": "Selection - Erabareshi Mono"}
			]
		},
		{
			"group": "Tail 'Gator",
			"titles": [
				{"searchTerm": "Tail 'Gator"},
				{"searchTerm": "Shippo de Bun"}
			]
		},
		{
			"group": "Taito Variety Pack",
			"titles": [
				{"searchTerm": "Taito Variety Pack"},
				{"searchTerm": "Mani 4 in 1 - Bubble Bobble + Elevator Action + Chase H.Q. + Sagaia"}
			]
		},
		{
			"group": "Taiyou no Tenshi Marlowe - Ohanabatake wa Dai-panic",
			"titles": [
				{"searchTerm": "Taiyou no Tenshi Marlowe - Ohanabatake wa Dai-panic"},
				{"searchTerm": "Philip & Marlowe in Bloomland", "priority": 2}
			]
		},
		{
			"group": "Tamagotchi",
			"titles": [
				{"searchTerm": "Tamagotchi"},
				{"searchTerm": "Game de Hakken!! Tamagotchi"}
			]
		},
		{
			"group": "Tasmania Story",
			"titles": [
				{"searchTerm": "Tasmania Story"},
				{"searchTerm": "Tasmania Monogatari"}
			]
		},
		{
			"group": "Taz-Mania 2",
			"titles": [
				{"searchTerm": "Taz-Mania 2"},
				{"searchTerm": "Taz-Mania"}
			]
		},
		{
			"group": "Tecmo Bowl",
			"titles": [
				{"searchTerm": "Tecmo Bowl"},
				{"searchTerm": "Tecmo Bowl GB"}
			]
		},
		{
			"group": "Teenage Mutant Ninja Turtles - Fall of the Foot Clan",
			"titles": [
				{"searchTerm": "Teenage Mutant Ninja Turtles - Fall of the Foot Clan"},
				{"searchTerm": "Teenage Mutant Hero Turtles - Fall of the Foot Clan"},
				{"searchTerm": "Teenage Mutant Ninja Turtles"}
			]
		},
		{
			"group": "Teenage Mutant Ninja Turtles II - Back from the Sewers",
			"titles": [
				{"searchTerm": "Teenage Mutant Ninja Turtles II - Back from the Sewers"},
				{"searchTerm": "Teenage Mutant Hero Turtles II - Back from the Sewers"},
				{"searchTerm": "Teenage Mutant Ninja Turtles 2"}
			]
		},
		{
			"group": "Teenage Mutant Ninja Turtles III - Radical Rescue",
			"titles": [
				{"searchTerm": "Teenage Mutant Ninja Turtles III - Radical Rescue"},
				{"searchTerm": "Teenage Mutant Hero Turtles III - Radical Rescue"},
				{"searchTerm": "Teenage Mutant Ninja Turtles 3 - Turtles Kikiippatsu"}
			]
		},
		{
			"group": "Tennis",
			"titles": [
				{"searchTerm": "Tennis"}
			],
			"compilations": [
				{"searchTerm": "Mani 4 in 1 - Tetris + Alleyway + Yakuman + Tennis", "titlePosition": 4}
			]
		},
		{
			"group": "Tetris",
			"titles": [
				{"searchTerm": "Tetris"}
			],
			"compilations": [
				{"searchTerm": "Mani 4 in 1 - Tetris + Alleyway + Yakuman + Tennis", "titlePosition": 1}
			]
		},
		{
			"group": "Tetris 2",
			"titles": [
				{"searchTerm": "Tetris 2"},
				{"searchTerm": "Tetris Flash"}
			]
		},
		{
			"group": "Tetris Attack",
			"titles": [
				{"searchTerm": "Tetris Attack"},
				{"searchTerm": "Yoshi no Panepon"}
			]
		},
		{
			"group": "Tetris Blast",
			"titles": [
				{"searchTerm": "Tetris Blast"},
				{"searchTerm": "Super Bombliss"}
			]
		},
		{
			"group": "Tiny Toon Adventures - Babs' Big Break",
			"titles": [
				{"searchTerm": "Tiny Toon Adventures - Babs' Big Break"},
				{"searchTerm": "Tiny Toon Adventures"}
			]
		},
		{
			"group": "Tiny Toon Adventures - Wacky Sports",
			"titles": [
				{"searchTerm": "Tiny Toon Adventures - Wacky Sports"},
				{"searchTerm": "Tiny Toon Adventures 3 - Dokidoki Sport Festival"}
			]
		},
		{
			"group": "Tiny Toon Adventures 2 - Montana's Movie Madness",
			"titles": [
				{"searchTerm": "Tiny Toon Adventures 2 - Montana's Movie Madness"},
				{"searchTerm": "Tiny Toon Adventures 2 - Buster Bunny no Kattobi Daibouken"}
			]
		},
		{
			"group": "Tip Off",
			"titles": [
				{"searchTerm": "Tip Off"},
				{"searchTerm": "GB Basketball"}
			]
		},
		{
			"group": "Tom & Jerry",
			"titles": [
				{"searchTerm": "Tom & Jerry"},
				{"searchTerm": "Tom to Jerry"}
			]
		},
		{
			"group": "Tom and Jerry - Frantic Antics!",
			"titles": [
				{"searchTerm": "Tom and Jerry - Frantic Antics!"},
				{"searchTerm": "Tom to Jerry Part 2"}
			]
		},
		{
			"group": "Top Rank Tennis",
			"titles": [
				{"searchTerm": "Top Rank Tennis"},
				{"searchTerm": "Top Ranking Tennis"}
			]
		},
		{
			"group": "Track & Field",
			"titles": [
				{"searchTerm": "Track & Field"},
				{"searchTerm": "Konamic Sports in Barcelona"}
			]
		},
		{
			"group": "Track Meet",
			"titles": [
				{"searchTerm": "Track Meet"},
				{"searchTerm": "Litti's Summer Sports"},
				{"searchTerm": "Track Meet - Mezase! Barcelona"}
			]
		},
		{
			"group": "Traumatarium",
			"titles": [
				{"searchTerm": "Traumatarium"},
				{"searchTerm": "Traumatarium (Broke Studio)", "priority": 2}
			]
		},
		{
			"group": "Trax",
			"titles": [
				{"searchTerm": "Trax"},
				{"searchTerm": "Totsugeki! Ponkotsu Tank"}
			]
		},
		{
			"group": "Turn and Burn - The F-14 Dogfight Simulator",
			"titles": [
				{"searchTerm": "Turn and Burn - The F-14 Dogfight Simulator"},
				{"searchTerm": "Phantom Air Mission"}
			]
		},
		{
			"group": "Ultima - Runes of Virtue",
			"titles": [
				{"searchTerm": "Ultima - Runes of Virtue"},
				{"searchTerm": "Ultima - Ushinawareta Runes"}
			]
		},
		{
			"group": "Ultima - Runes of Virtue II",
			"titles": [
				{"searchTerm": "Ultima - Runes of Virtue II"},
				{"searchTerm": "Ultima - Ushinawareta Runes 2"}
			]
		},
		{
			"group": "Ultra Golf",
			"titles": [
				{"searchTerm": "Ultra Golf"},
				{"searchTerm": "Konami Golf"},
				{"searchTerm": "Konamic Golf"}
			]
		},
		{
			"group": "Wario Blast Featuring Bomberman!",
			"titles": [
				{"searchTerm": "Wario Blast Featuring Bomberman!"}
			],
			"compilations": [
				{"searchTerm": "Bomberman Collection"}
			]
		},
		{
			"group": "We're Back! - A Dinosaur's Story",
			"titles": [
				{"searchTerm": "We're Back! - A Dinosaur's Story"},
				{"searchTerm": "Agro Soar"},
				{"searchTerm": "Baby T-Rex"},
				{"searchTerm": "Bamse"},
				{"searchTerm": "Edd the Duck"}
			]
		},
		{
			"group": "Wheel of Fortune",
			"titles": [
				{"searchTerm": "Wheel of Fortune"},
				{"searchTerm": "Gluecksrad"}
			]
		},
		{
			"group": "Wild Snake",
			"titles": [
				{"searchTerm": "Wild Snake"},
				{"searchTerm": "Super Snakey"}
			]
		},
		{
			"group": "Winter Olympic Games",
			"titles": [
				{"searchTerm": "Winter Olympic Games"},
				{"searchTerm": "Winter Gold"}
			]
		},
		{
			"group": "World Beach Volley - 1992 GB Cup",
			"titles": [
				{"searchTerm": "World Beach Volley - 1992 GB Cup"},
				{"searchTerm": "World Beach Volley - 1991 GB Cup"}
			]
		},
		{
			"group": "World Circuit Series",
			"titles": [
				{"searchTerm": "World Circuit Series"},
				{"searchTerm": "F-1 Spirit"},
				{"searchTerm": "Spirit of F-1, The"}
			]
		},
		{
			"group": "World Heroes 2 Jet",
			"titles": [
				{"searchTerm": "World Heroes 2 Jet"},
				{"searchTerm": "Nettou World Heroes 2 Jet"}
			]
		},
		{
			"group": "X",
			"titles": [
				{"searchTerm": "X"},
				{"searchTerm": "Lunar Chase"}
			]
		},
		{
			"group": "Xenon 2",
			"titles": [
				{"searchTerm": "Xenon 2"},
				{"searchTerm": "Xenon 2 - Megablast"}
			]
		},
		{
			"group": "Yakuman",
			"titles": [
				{"searchTerm": "Yakuman"}
			],
			"compilations": [
				{"searchTerm": "Mani 4 in 1 - Tetris + Alleyway + Yakuman + Tennis", "titlePosition": 3}
			]
		},
		{
			"group": "Yelu Wangzi (Prince Yeh Rude)",
			"titles": [
				{"searchTerm": "Yelu Wangzi (Prince Yeh Rude)", "localNames": {"chinese (traditional)": "耶魯王子"}}
			]
		},
		{
			"group": "Yoshi",
			"titles": [
				{"searchTerm": "Yoshi"},
				{"searchTerm": "Mario & Yoshi"},
				{"searchTerm": "Yoshi no Tamago"}
			]
		},
		{
			"group": "Yoshi's Cookie",
			"titles": [
				{"searchTerm": "Yoshi's Cookie"},
				{"searchTerm": "Yoshi no Cookie"}
			]
		},
		{
			"group": "Zettai Muteki Raijin-Oh",
			"titles": [
				{"searchTerm": "Zettai Muteki Raijin-Oh"}
			],
			"compilations": [
				{"searchTerm": "Mani 4 in 1 - Genki Bakuhatsu Gambaruger + Zettai Muteki Raijin-Oh + Zoids Densetsu + Miracle Adventure of Esparks - Ushinawareta Seiseki Perivron", "titlePosition": 2}
			]
		},
		{
			"group": "Zoids Densetsu",
			"titles": [
				{"searchTerm": "Zoids Densetsu"}
			],
			"compilations": [
				{"searchTerm": "Mani 4 in 1 - Genki Bakuhatsu Gambaruger + Zettai Muteki Raijin-Oh + Zoids Densetsu + Miracle Adventure of Esparks - Ushinawareta Seiseki Perivron", "titlePosition": 3}
			]
		},
		{
			"group": "Zool - Ninja of the 'Nth' Dimension",
			"titles": [
				{"searchTerm": "Zool - Ninja of the 'Nth' Dimension"},
				{"searchTerm": "Zool"}
			]
		},
		{
			"group": "Zuigao Jimi",
			"titles": [
				{"searchTerm": "Zuigao Jimi (Top Secret)", "localNames": {"chinese (traditional)": "最高機密"}},
				{"searchTerm": "Zuigao Jimi (Top Secret) (Multicart Rip)", "priority": 2, "localNames": {"chinese (traditional)": "最高機密"}}
			]
		}
	]
}
